aes/accumulator.sv

module accumulator(
    input logic clk,
    input logic rst_n,

    input logic[31:0] input_data,
    input logic input_valid,
    input logic input_last,

    output logic[127:0] output_data,
    output logic output_valid

);

// Should make this generic but have not 

    logic [127:0] accumulator;
    logic [127:0] accumulator_next;
    logic [1:0] word_count;

    always @(posedge clk) begin
        if (!rst_n) begin 
            accumulator <= '0;
            word_count <= '0;
        end else begin 
            if (input_last) begin 
                word_count <= '0;
            end else if (input_valid) begin 
                word_count <= word_count + 1;
            end 
            accumulator <= accumulator_next;

            output_data <= accumulator_next;
            output_valid <= (word_count == 3 || input_last) && input_valid;
        end 
    end

    always_comb begin
        accumulator_next = '0;

        case (word_count)
            2'd0: accumulator_next = {input_data, 96'b0};

            2'd1: accumulator_next = {
                accumulator[127:96],
                input_data,
                64'b0
            };

            2'd2: accumulator_next = {
                accumulator[127:64],
                input_data,
                32'b0
            };

            2'd3: accumulator_next = {
                accumulator[127:32],
                input_data
            };

            default: accumulator_next = '0;
        endcase
    end

    // assign output_data = accumulator_next;
    // assign output_valid = (word_count == 3 || input_last) && input_valid;

endmodule

aes/accumulator.vcd
$version Generated by VerilatedVcd $end
$timescale 1ps $end
 $scope module TOP $end
  $var wire 1 ( clk $end
  $var wire 1 ) rst_n $end
  $var wire 32 * input_data [31:0] $end
  $var wire 1 + input_valid $end
  $var wire 1 , input_last $end
  $var wire 128 - output_data [127:0] $end
  $var wire 1 1 output_valid $end
  $scope module accumulator $end
   $var wire 1 ( clk $end
   $var wire 1 ) rst_n $end
   $var wire 32 * input_data [31:0] $end
   $var wire 1 + input_valid $end
   $var wire 1 , input_last $end
   $var wire 128 - output_data [127:0] $end
   $var wire 1 1 output_valid $end
   $var wire 128 # accumulator [127:0] $end
   $var wire 128 2 accumulator_next [127:0] $end
   $var wire 2 ' word_count [1:0] $end
  $upscope $end
 $upscope $end
$enddefinitions $end


#0
b00000000000000000000000000000000000000000000000000000000000000000000000000000000000000000000000000000000000000000000000000000000 #
b00 '
0(
0)
b00000000000000000000000000000000 *
0+
0,
b00000000000000000000000000000000000000000000000000000000000000000000000000000000000000000000000000000000000000000000000000000000 -
01
b00000000000000000000000000000000000000000000000000000000000000000000000000000000000000000000000000000000000000000000000000000000 2
#1
1(
#2
0(
#3
1(
#4
0(
1)
b00000000000000000000000000000001 *
1+
b00000000000000000000000000000001000000000000000000000000000000000000000000000000000000000000000000000000000000000000000000000000 2
#5
b00000000000000000000000000000001000000000000000000000000000000000000000000000000000000000000000000000000000000000000000000000000 #
b01 '
1(
b00000000000000000000000000000001000000000000000000000000000000000000000000000000000000000000000000000000000000000000000000000000 -
b00000000000000000000000000000001000000000000000000000000000000010000000000000000000000000000000000000000000000000000000000000000 2
#6
0(
b00000000000000000000000000000010 *
b00000000000000000000000000000001000000000000000000000000000000100000000000000000000000000000000000000000000000000000000000000000 2
#7
b00000000000000000000000000000001000000000000000000000000000000100000000000000000000000000000000000000000000000000000000000000000 #
b10 '
1(
b00000000000000000000000000000001000000000000000000000000000000100000000000000000000000000000000000000000000000000000000000000000 -
b00000000000000000000000000000001000000000000000000000000000000100000000000000000000000000000001000000000000000000000000000000000 2
#8
0(
b00000000000000000000000000000011 *
b00000000000000000000000000000001000000000000000000000000000000100000000000000000000000000000001100000000000000000000000000000000 2
#9
b00000000000000000000000000000001000000000000000000000000000000100000000000000000000000000000001100000000000000000000000000000000 #
b11 '
1(
b00000000000000000000000000000001000000000000000000000000000000100000000000000000000000000000001100000000000000000000000000000000 -
b00000000000000000000000000000001000000000000000000000000000000100000000000000000000000000000001100000000000000000000000000000011 2
#10
0(
b00000000000000000000000000000100 *
b00000000000000000000000000000001000000000000000000000000000000100000000000000000000000000000001100000000000000000000000000000100 2
#11
b00000000000000000000000000000001000000000000000000000000000000100000000000000000000000000000001100000000000000000000000000000100 #
b00 '
1(
b00000000000000000000000000000001000000000000000000000000000000100000000000000000000000000000001100000000000000000000000000000100 -
11
b00000000000000000000000000000100000000000000000000000000000000000000000000000000000000000000000000000000000000000000000000000000 2
#12
0(
b00000000000000000000000000000101 *
b00000000000000000000000000000101000000000000000000000000000000000000000000000000000000000000000000000000000000000000000000000000 2
#13
b00000000000000000000000000000101000000000000000000000000000000000000000000000000000000000000000000000000000000000000000000000000 #
b01 '
1(
b00000000000000000000000000000101000000000000000000000000000000000000000000000000000000000000000000000000000000000000000000000000 -
01
b00000000000000000000000000000101000000000000000000000000000001010000000000000000000000000000000000000000000000000000000000000000 2
#14
0(
b00000000000000000000000000000110 *
b00000000000000000000000000000101000000000000000000000000000001100000000000000000000000000000000000000000000000000000000000000000 2
#15
b00000000000000000000000000000101000000000000000000000000000001100000000000000000000000000000000000000000000000000000000000000000 #
b10 '
1(
b00000000000000000000000000000101000000000000000000000000000001100000000000000000000000000000000000000000000000000000000000000000 -
b00000000000000000000000000000101000000000000000000000000000001100000000000000000000000000000011000000000000000000000000000000000 2
#16
0(
b00000000000000000000000000000111 *
b00000000000000000000000000000101000000000000000000000000000001100000000000000000000000000000011100000000000000000000000000000000 2
#17
b00000000000000000000000000000101000000000000000000000000000001100000000000000000000000000000011100000000000000000000000000000000 #
b11 '
1(
b00000000000000000000000000000101000000000000000000000000000001100000000000000000000000000000011100000000000000000000000000000000 -
b00000000000000000000000000000101000000000000000000000000000001100000000000000000000000000000011100000000000000000000000000000111 2
#18
0(
b00000000000000000000000000001000 *
1,
b00000000000000000000000000000101000000000000000000000000000001100000000000000000000000000000011100000000000000000000000000001000 2
#19
b00000000000000000000000000000101000000000000000000000000000001100000000000000000000000000000011100000000000000000000000000001000 #
b00 '
1(
b00000000000000000000000000000101000000000000000000000000000001100000000000000000000000000000011100000000000000000000000000001000 -
11
b00000000000000000000000000001000000000000000000000000000000000000000000000000000000000000000000000000000000000000000000000000000 2
#20
0(
0+
#21
b00000000000000000000000000001000000000000000000000000000000000000000000000000000000000000000000000000000000000000000000000000000 #
1(
b00000000000000000000000000001000000000000000000000000000000000000000000000000000000000000000000000000000000000000000000000000000 -
01
